odoo/addons/stock_move_location_purchase_uom/README.rst
odoo/addons/stock_move_location_purchase_uom/__init__.py
odoo/addons/stock_move_location_purchase_uom/__manifest__.py
odoo/addons/stock_move_location_purchase_uom/i18n/it.po
odoo/addons/stock_move_location_purchase_uom/i18n/stock_move_location_purchase_uom.pot
odoo/addons/stock_move_location_purchase_uom/readme/CONTRIBUTORS.md
odoo/addons/stock_move_location_purchase_uom/readme/DESCRIPTION.md
odoo/addons/stock_move_location_purchase_uom/static/description/icon.png
odoo/addons/stock_move_location_purchase_uom/static/description/index.html
odoo/addons/stock_move_location_purchase_uom/tests/__init__.py
odoo/addons/stock_move_location_purchase_uom/tests/test_move_location_purchase_uom.py
odoo/addons/stock_move_location_purchase_uom/wizard/__init__.py
odoo/addons/stock_move_location_purchase_uom/wizard/stock_move_location.py
odoo_addon_stock_move_location_purchase_uom-18.0.1.0.0.4.dist-info/METADATA
odoo_addon_stock_move_location_purchase_uom-18.0.1.0.0.4.dist-info/WHEEL
odoo_addon_stock_move_location_purchase_uom-18.0.1.0.0.4.dist-info/top_level.txt
odoo_addon_stock_move_location_purchase_uom-18.0.1.0.0.4.dist-info/RECORD
