Metadata-Version: 2.1
Name: odoo-addon-stock_move_location_purchase_uom
Version: 18.0.1.0.0.4
Requires-Python: >=3.10
Requires-Dist: odoo-addon-stock_move_location==18.0.*
Requires-Dist: odoo-addon-stock_move_purchase_uom==18.0.*
Requires-Dist: odoo==18.0.*
Summary: This module 'glues' the modules stock_move_location and stock_move_purchase_uom.
Home-page: https://github.com/OCA/stock-logistics-warehouse
License: AGPL-3
Author: ForgeFlow, Odoo Community Association (OCA)
Author-email: support@odoo-community.org
Classifier: Programming Language :: Python
Classifier: Framework :: Odoo
Classifier: Framework :: Odoo :: 18.0
Classifier: License :: OSI Approved :: GNU Affero General Public License v3
